{"note":"This file is an internal implementation detail to speed up HTML report generation. Its format can change at any time. You might be looking for the JSON report: https://coverage.rtfd.io/cmd.html#cmd-json","format":5,"version":"7.5.3","globals":"11fec2a2f9fb4c32114581b68935cc5e","files":{"dummy_server_py":{"hash":"d219d64a2248e13769443cf674dd46d7","index":{"url":"dummy_server_py.html","file":"dummy_server.py","description":"","nums":{"precision":0,"n_files":1,"n_statements":51,"n_excluded":0,"n_missing":10,"n_branches":0,"n_partial_branches":0,"n_missing_branches":0}}},"server_py":{"hash":"eff1a2304b718056163751273d94cf93","index":{"url":"server_py.html","file":"server.py","description":"","nums":{"precision":0,"n_files":1,"n_statements":63,"n_excluded":0,"n_missing":11,"n_branches":0,"n_partial_branches":0,"n_missing_branches":0}}},"utils_py":{"hash":"2b6f4ba1e32ed9580582c5780460e799","index":{"url":"utils_py.html","file":"utils.py","description":"","nums":{"precision":0,"n_files":1,"n_statements":173,"n_excluded":0,"n_missing":43,"n_branches":0,"n_partial_branches":0,"n_missing_branches":0}}},"webscraping_py":{"hash":"3602118d2492a965346dc3f49d6589e4","index":{"url":"webscraping_py.html","file":"webscraping.py","description":"","nums":{"precision":0,"n_files":1,"n_statements":269,"n_excluded":0,"n_missing":172,"n_branches":0,"n_partial_branches":0,"n_missing_branches":0}}}}}